Lightflow_Epics-1.2.2.dist-info/DESCRIPTION.rst
Lightflow_Epics-1.2.2.dist-info/METADATA
Lightflow_Epics-1.2.2.dist-info/RECORD
Lightflow_Epics-1.2.2.dist-info/WHEEL
Lightflow_Epics-1.2.2.dist-info/metadata.json
Lightflow_Epics-1.2.2.dist-info/top_level.txt
lightflow_epics/__init__.py
lightflow_epics/pv_trigger_task.py
